falconry_pygments_theme/__init__.py
falconry_pygments_theme/common.py
falconry_pygments_theme/dark.py
falconry_pygments_theme/light.py
falconry_pygments_theme-0.2.0.dist-info/LICENSE
falconry_pygments_theme-0.2.0.dist-info/METADATA
falconry_pygments_theme-0.2.0.dist-info/WHEEL
falconry_pygments_theme-0.2.0.dist-info/entry_points.txt
falconry_pygments_theme-0.2.0.dist-info/top_level.txt
falconry_pygments_theme-0.2.0.dist-info/RECORD
