Metadata-Version: 2.1
Name: falconry-pygments-theme
Version: 0.2.0
Summary: Falconry Pygments styles
Author-email: Vytautas Liuolia <vytautas.liuolia@gmail.com>
License: Apache 2.0
Project-URL: Homepage, https://github.com/falconry/pygments-theme
Project-URL: Funding, https://opencollective.com/falcon
Project-URL: Chat, https://gitter.im/falconry/dev
Project-URL: Source, https://github.com/falconry/pygments-theme
Keywords: falcon-framework,pygments,pygments-style
Classifier: Development Status :: 3 - Alpha
Classifier: Intended Audience :: Developers
Classifier: License :: OSI Approved :: Apache Software License
Classifier: Operating System :: OS Independent
Classifier: Programming Language :: Python :: 3
Classifier: Programming Language :: Python :: 3.8
Classifier: Programming Language :: Python :: 3.9
Classifier: Programming Language :: Python :: 3.10
Classifier: Programming Language :: Python :: 3.11
Classifier: Programming Language :: Python :: 3.12
Classifier: Programming Language :: Python :: 3.13
Classifier: Topic :: Software Development :: Libraries :: Python Modules
Requires-Python: >=3.8
License-File: LICENSE
Requires-Dist: pygments >=1.5
